venvify/__init__.py
venvify/venvify.py
venvify-0.0.2.dist-info/LICENSE
venvify-0.0.2.dist-info/METADATA
venvify-0.0.2.dist-info/WHEEL
venvify-0.0.2.dist-info/entry_points.txt
venvify-0.0.2.dist-info/top_level.txt
venvify-0.0.2.dist-info/RECORD
