Metadata-Version: 2.1
Name: venvify
Version: 0.0.2
Summary: Turn Python installations into venv-like environments that you can activate
Home-page: https://github.com/Victorlouisdg/venvify
Author: Victor-Louis De Gusseme
Author-email: victorlouisdg@gmail.com
License: UNKNOWN
Project-URL: Bug Tracker, https://github.com/Victorlouisdg/venvify/issues
Platform: UNKNOWN
Classifier: Programming Language :: Python :: 3
Classifier: License :: OSI Approved :: MIT License
Classifier: Operating System :: OS Independent
Requires-Python: >=3.6
License-File: LICENSE
